smbmc/.pytest_cache/.gitignore
smbmc/.pytest_cache/CACHEDIR.TAG
smbmc/.pytest_cache/README.md
smbmc/.pytest_cache/v/cache/nodeids
smbmc/.pytest_cache/v/cache/stepwise
smbmc/__init__.py
smbmc/client.py
smbmc/ipmi_pmbus.py
smbmc/ipmi_sensor.py
smbmc/models.py
smbmc/util.py
smbmc-0.2.0.dist-info/LICENSE
smbmc-0.2.0.dist-info/WHEEL
smbmc-0.2.0.dist-info/METADATA
smbmc-0.2.0.dist-info/RECORD
