Metadata-Version: 2.1
Name: smbmc
Version: 0.2.0
Summary: Supermicro BMC interface
Home-page: https://github.com/grawlinson/smbmc
Author: George Rawlinson
Author-email: george@rawlinson.net.nz
Requires-Python: >=3.6.1,<4.0.0
Classifier: Development Status :: 4 - Beta
Classifier: Intended Audience :: Developers
Classifier: Intended Audience :: System Administrators
Classifier: License :: OSI Approved :: GNU General Public License v3 (GPLv3)
Classifier: Programming Language :: Python :: 3
Classifier: Programming Language :: Python :: 3.6
Classifier: Programming Language :: Python :: 3.7
Classifier: Programming Language :: Python :: 3.8
Classifier: Programming Language :: Python :: 3.9
Classifier: Topic :: System :: Monitoring
Classifier: Topic :: Utilities
Requires-Dist: defusedxml (>=0.6.0,<0.7.0)
Requires-Dist: requests (>=2.24.0,<3.0.0)
Project-URL: Repository, https://github.com/grawlinson/smbmc
